[
  {
    "scholarship_name": "Bath Global Excellence Scholarship 2026",
    "type": "Scholarship",
    "tags": {
      "state": "United Kingdom",
      "gender": "All",
      "religion": "All",
      "class": [
        "Class 10",
        "Class 12",
        "UG",
        "PG"
      ]
    },
    "eligibility": "Students joining a full-time taught Master’s course in September 2026 at the University of Bath are eligible.",
    "scholarship_amount": "£10,000",
    "application_deadline": "04-Feb-2026",
    "apply_link": "https://www.bath.ac.uk/campaigns/bath-global-excellence-scholarship/",
    "url": "https://www.buddy4study.com/scholarship/bath-global-excellence-scholarship"
  },
  {
    "scholarship_name": "ICJ Judicial Fellowship Programme 2026",
    "type": "Fellowship",
    "tags": {
      "state": "The Netherlands",
      "gender": "All",
      "religion": "All",
      "class": [
        "Class 10",
        "Class 12",
        "UG",
        "PG"
      ]
    },
    "eligibility": "Recent law graduates who are 31 years old or younger, with excellent academic results and an interest in public international law, nominated by their universities.",
    "scholarship_amount": "10 months of professional experience, along with financial assistance, travel and health insurance costs",
    "application_deadline": "05-Feb-2026",
    "apply_link": "https://www.icj-cij.org/judicial-fellows-program",
    "url": "https://www.buddy4study.com/scholarship/icj-judicial-fellowship-programme-2026"
  },
  {
    "scholarship_name": "FIDH ICC Internship 2026",
    "type": "Internship",
    "tags": {
      "state": "Netherlands",
      "gender": "All",
      "religion": "All",
      "class": [
        "Law",
        "Political Science",
        "International Relations",
        "UG",
        "PG"
      ]
    },
    "eligibility": "Pursuing studies in International Law, Criminal Law, Political Science, International Relations, or a related field, with an interest in human rights or international justice.",
    "scholarship_amount": "Monthly stipend, daily contribution toward meal expenses, reimbursement of travel expenses, 12 days RTT, and 2 days paid holiday per month",
    "application_deadline": "06-Feb-2026",
    "apply_link": "https://www.fidh.org/en/com/recruitment/internship-with-the-international-federation-for-human-rights-fidh-32442",
    "url": "https://www.buddy4study.com/scholarship/fidh-icc-internship-2026"
  },
  {
    "scholarship_name": "Teach for India Fellowship 2026",
    "type": "Scholarship",
    "tags": {
      "state": "All India",
      "gender": "All",
      "religion": "All",
      "class": [
        "Class 10",
        "Class 12",
        "UG",
        "PG"
      ]
    },
    "eligibility": "Applicants must be Indian citizens or Overseas Citizens of India, have completed graduation by June/July 2026, and apply between July 2025 and May 2026.",
    "scholarship_amount": "₹25,344 per month, housing allowance of ₹6,000–12,600, reimbursements for work-related expenses, health insurance of up to ₹1,00,000, and access to career fair after the Fellowship.",
    "application_deadline": "08-Feb-2026",
    "apply_link": "https://www.buddy4study.com/scholarship/teach-for-india-fellowship",
    "url": "https://www.buddy4study.com/scholarship/teach-for-india-fellowship"
  },
  {
    "scholarship_name": "ANRF J. C. Bose Grant (JBG) 2026",
    "type": "Scholarship",
    "tags": {
      "state": "All India",
      "gender": "All",
      "religion": "All",
      "class": [
        "Senior scientist/engineer",
        "UG",
        "PG",
        "PhD"
      ]
    },
    "eligibility": "Applicants must be Indian nationals, 45-65 years of age, active and senior scientists/engineers with a record of outstanding performance in the field of science and technology.",
    "scholarship_amount": "₹26,00,000 per year (research grant) and ₹1,00,000 per year (fixed overheads to the implementing institution)",
    "application_deadline": "10-Feb-2026",
    "apply_link": "https://anrfonline.in/ANRF/HomePage",
    "url": "https://www.buddy4study.com/scholarship/anrf-j-c-bose-grant-jbg-2026"
  },
  {
    "scholarship_name": "BOC Scholarship Odisha 2025-26",
    "type": "Scholarship",
    "tags": {
      "state": "Odisha",
      "gender": "All",
      "religion": "General / ST / SC / OBC / SEBC",
      "class": [
        "I.T.I",
        "I.T.C",
        "Polytechnic",
        "Diploma"
      ]
    },
    "eligibility": "Applicant must be a permanent resident of Odisha, belong to General, ST, SC, OBC and SEBC categories, and be an I.T.I./I.T.C.Polytechnic/Diploma student.",
    "scholarship_amount": "Variable financial assistance",
    "application_deadline": "12-Feb-2026",
    "apply_link": "https://scholarship.odisha.gov.in/website/scholarship-details",
    "url": "https://www.buddy4study.com/scholarship/boc-scholarship-odisha-2025"
  },
  {
    "scholarship_name": "University of Oregon ICSP Scholarship 2026",
    "type": "Scholarship",
    "tags": {
      "state": "United States",
      "gender": "All",
      "religion": "All",
      "class": [
        "Class 10",
        "Class 12",
        "UG",
        "PG",
        "PhD"
      ]
    },
    "eligibility": "International students at the University of Oregon who are admissible or fully admitted, not U.S. citizens, U.S. permanent residents, or eligible to receive U.S. federal financial assistance, and have a minimum cumulative GPA of 3.5.",
    "scholarship_amount": "Partial tuition waiver",
    "application_deadline": "13-Feb-2026",
    "apply_link": "https://isss.uoregon.edu/icsp/application",
    "url": "https://www.buddy4study.com/scholarship/university-of-oregon-icsp-scholarship-2026"
  },
  {
    "scholarship_name": "Reuters-Oxford Journalism Fellowship Programme 2026-27",
    "type": "Scholarship",
    "tags": {
      "state": "All India",
      "gender": "All",
      "religion": "All",
      "class": [
        "Mid-career journalists"
      ]
    },
    "eligibility": "Applicants must have a minimum of five years' journalistic experience, be working as a journalist, and intend to return to journalistic work after completing the fellowship.",
    "scholarship_amount": "Monthly stipend of £2,000, travel expenses, visa expenses, and other benefits",
    "application_deadline": "13-Feb-2026",
    "apply_link": "https://reutersinstitute.politics.ox.ac.uk/our-journalist-fellowship-programme",
    "url": "https://www.buddy4study.com/scholarship/reuters-oxford-journalism-fellowship-programme-2026"
  },
  {
    "scholarship_name": "Nehru Trust's UK Travel Awards 2026-27",
    "type": "Scholarship",
    "tags": {
      "state": "All India",
      "gender": "All",
      "religion": "All",
      "class": [
        "Scholars",
        "Professionals"
      ]
    },
    "eligibility": "Indian citizens, scholars or professionals working in museums, galleries, universities or other specified institutions concerned with the preservation, study and display of India's art and cultural heritage.",
    "scholarship_amount": "Up to £1,500 and airfare",
    "application_deadline": "15-Feb-2026",
    "apply_link": "http://www.nehrutrustvam.org/awards/uk-travel-awards",
    "url": "https://www.buddy4study.com/scholarship/nehru-trusts-uk-travel-awards-2026"
  },
  {
    "scholarship_name": "Government of Brunei Darussalam Scholarship 2026-27",
    "type": "Scholarship",
    "tags": {
      "state": "Brunei",
      "gender": "All",
      "religion": "All",
      "class": [
        "Class 10",
        "Class 12",
        "UG",
        "PG"
      ]
    },
    "eligibility": "Students having applied for UG and PG degree programmes, not exceeding 25 years for UG and Diploma courses, and 35 years for PG Master's degree courses, with English language proficiency.",
    "scholarship_amount": "Full tuition fee, monthly personal allowance of BND$500.00, monthly meals allowance of BND$150.00, annual book allowance of BND$600.00, accommodation, baggage allowance, and comprehensive insurance coverage.",
    "application_deadline": "15-Feb-2026",
    "apply_link": "https://www.buddy4study.com/scholarship/government-of-brunei-darussalam-scholarship",
    "url": "https://www.buddy4study.com/scholarship/government-of-brunei-darussalam-scholarship"
  },
  {
    "scholarship_name": "IIM Rohtak Doctoral Programme in Management 2026-30",
    "type": "Scholarship",
    "tags": {
      "state": "All India",
      "gender": "All",
      "religion": "All",
      "class": [
        "PhD",
        "UG",
        "PG"
      ]
    },
    "eligibility": "Applicants must have a Post-Graduate degree or equivalent in any discipline with at least 55% marks or an equivalent CGPA, or meet other specified qualifications.",
    "scholarship_amount": "Up to ₹50,000 per month with other benefits",
    "application_deadline": "17-Feb-2026",
    "apply_link": "https://www.buddy4study.com/scholarship/iim-rohtak-doctoral-programme-in-management-2026",
    "url": "https://www.buddy4study.com/scholarship/iim-rohtak-doctoral-programme-in-management-2026"
  },
  {
    "scholarship_name": "Turkiye Scholarships 2026",
    "type": "Scholarship",
    "tags": {
      "state": "International",
      "gender": "All",
      "religion": "All",
      "class": [
        "Associate",
        "UG",
        "PG",
        "PhD"
      ]
    },
    "eligibility": "International students pursuing associate, UG, PG, and PhD levels at universities in Turkey, with age limits and academic requirements.",
    "scholarship_amount": "Up to ₺9,000 and other benefits",
    "application_deadline": "20-Feb-2026",
    "apply_link": "https://www.buddy4study.com/scholarship/turkiye-scholarships-2026",
    "url": "https://www.buddy4study.com/scholarship/turkiye-scholarships-2026"
  },
  {
    "scholarship_name": "UCL India Excellence Scholarship 2026-27",
    "type": "Scholarship",
    "tags": {
      "state": "India",
      "gender": "All",
      "religion": "All",
      "class": [
        "Class 10",
        "Class 12",
        "UG",
        "PG"
      ]
    },
    "eligibility": "Applicants must be permanently domiciled in India, hold a bachelor's degree or be enrolled in the final year of a bachelor's degree, and have secured a GPA equivalent to a UK first-class degree.",
    "scholarship_amount": "GBP 5,000 (approximately ₹6,27,846)",
    "application_deadline": "26-Feb-2026",
    "apply_link": "https://www.buddy4study.com/scholarship/ucl-india-excellence-scholarship-2026",
    "url": "https://www.buddy4study.com/scholarship/ucl-india-excellence-scholarship-2026"
  },
  {
    "scholarship_name": "F. M. Kirby Foundation Internship Program 2026",
    "type": "Internship",
    "tags": {
      "state": "New Jersey",
      "gender": "All",
      "religion": "All",
      "class": [
        "College Sophomore",
        "College Junior",
        "College Senior"
      ]
    },
    "eligibility": "Rising college sophomores, juniors, and seniors with a GPA of 3.2 or higher who qualified for need-based financial aid in the previous school year and have an interest in philanthropy or nonprofit management.",
    "scholarship_amount": "$23 per hour for approximately 20-25 hours per week over 10 weeks, and a one-time travel stipend",
    "application_deadline": "27-Feb-2026",
    "apply_link": "https://fmkirbyfoundation.org/internship-program/#",
    "url": "https://www.buddy4study.com/scholarship/f-m-kirby-foundation-internship-program-2026"
  },
  {
    "scholarship_name": "Ashinaga Foundation Spring-Summer Internship 2026",
    "type": "Internship",
    "tags": {
      "state": "Japan",
      "gender": "All",
      "religion": "All",
      "class": [
        "Graduate students",
        "Young professionals",
        "University students"
      ]
    },
    "eligibility": "University students, graduate students, and young professionals with a strong interest in social impact, education, or international development.",
    "scholarship_amount": "¥1,000 per working day",
    "application_deadline": "27-Feb-2026",
    "apply_link": "https://ashinagainternship.my.canva.site/en-home",
    "url": "https://www.buddy4study.com/scholarship/ashinaga-foundation-spring-summer-internship-2026"
  },
  {
    "scholarship_name": "MBZUAI Undergraduate Research Internship Program (UGRIP) 2025",
    "type": "Scholarship",
    "tags": {
      "state": "United Arab Emirates",
      "gender": "All",
      "religion": "All",
      "class": [
        "Class 10",
        "Class 12",
        "UG",
        "PG",
        "PhD"
      ]
    },
    "eligibility": "Undergraduate students in AI-related fields, minimum CGPA 3.5, 3 years of undergraduate study, strong academic performance, research potential, and proficiency in English.",
    "scholarship_amount": "Fully funded internship with additional benefits",
    "application_deadline": "28-Feb-2026",
    "apply_link": "https://mbzuai.ac.ae/ugrip/",
    "url": "https://www.buddy4study.com/scholarship/mbzuai-undergraduate-research-internship-program-ugrip-2025"
  },
  {
    "scholarship_name": "KWI International Fellowship Program 2026",
    "type": "Scholarship",
    "tags": {
      "state": "International",
      "gender": "All",
      "religion": "All",
      "class": [
        "PhD",
        "Postdoctoral"
      ]
    },
    "eligibility": "International postdoctoral and senior researchers with a PhD who are conducting research in cultural studies, humanities, or social sciences.",
    "scholarship_amount": "€3,000 monthly allowance",
    "application_deadline": "28-Feb-2026",
    "apply_link": "https://www.kulturwissenschaften.de/wp-content/uploads/2025/12/call-international-fellowships-october-26.pdf",
    "url": "https://www.buddy4study.com/scholarship/kwi-international-fellowship-program-2026"
  },
  {
    "scholarship_name": "Ute and György Széll International PhD Scholarship 2026-27",
    "type": "Scholarship",
    "tags": {
      "state": "Germany",
      "gender": "All",
      "religion": "All",
      "class": [
        "PhD"
      ]
    },
    "eligibility": "Enrolled PhD students in Social Sciences or Humanities with a research plan and invitation from a host PhD supervisor in Germany.",
    "scholarship_amount": "€1,450 monthly stipend, €1,300 annual allowance for travel expenses, and a six-month research stay at a German university or research institution.",
    "application_deadline": "28-Feb-2026",
    "apply_link": "https://www.boeckler.de/de/international-scholarships-33846.htm",
    "url": "https://www.buddy4study.com/scholarship/ute-and-gyorgy-szell-international-phd-scholarship-2026"
  },
  {
    "scholarship_name": "DMI Patna PGDM Scholarship 2026",
    "type": "Scholarship",
    "tags": {
      "state": "Bihar",
      "gender": "All",
      "religion": "All",
      "class": [
        "Class 10",
        "Class 12",
        "UG",
        "PG",
        "PhD"
      ]
    },
    "eligibility": "Applicants must hold a Bachelor's degree in any discipline, have a minimum of 50% aggregate marks, and have acquired a valid score in CAT 2025/XAT 2026/GMAT (2022-26)/CMAT 2026/MAT (September 2025 or later).",
    "scholarship_amount": "Up to 100% tuition fee waiver",
    "application_deadline": "28-Feb-2026",
    "apply_link": "https://www.buddy4study.com/scholarship/dmi-patna-pgdm-scholarship-2026",
    "url": "https://www.buddy4study.com/scholarship/dmi-patna-pgdm-scholarship-2026"
  },
  {
    "scholarship_name": "Norwegian BI Presidential Scholarship 2026",
    "type": "Scholarship",
    "tags": {
      "state": "Norway",
      "gender": "All",
      "religion": "All",
      "class": [
        "Class 10",
        "Class 12",
        "UG",
        "PG",
        "PhD"
      ]
    },
    "eligibility": "Norwegian and international students residing in Norway with a minimum overall GPA of 'A' on the ECTS scale or the equivalent top-level grade on international grade scales, admitted to the first year of a Master of Science degree programme at campus Oslo or campus Bergen.",
    "scholarship_amount": "Full tuition-fee for up to 2 years and a stipend of NOK 50,000 (approx. ₹ 4,43,329) per semester",
    "application_deadline": "01-Mar-2026",
    "apply_link": "https://www.bi.no/en/programmes-and-individual-courses/scholarships/bi-presidential-scholarships/#how-to-apply_365139",
    "url": "https://www.buddy4study.com/scholarship/norwegian-bi-presidential-scholarship"
  },
  {
    "scholarship_name": "Heinrich Böll Foundation Doctoral Scholarship 2026",
    "type": "Scholarship",
    "tags": {
      "state": "Germany / International / All India",
      "gender": "All",
      "religion": "All",
      "class": [
        "Class 10",
        "Class 12",
        "UG",
        "PG",
        "PhD"
      ]
    },
    "eligibility": "Doctoral students from Germany or other countries are eligible for this scholarship.",
    "scholarship_amount": "€1650 per month, €100 mobility allowance per month, and other individual allowances",
    "application_deadline": "01-Mar-2026",
    "apply_link": "https://www.boell.de/de/stipendium-promotion",
    "url": "https://www.buddy4study.com/scholarship/heinrich-boll-foundation-doctoral-scholarship"
  },
  {
    "scholarship_name": "University of Glasgow India Excellence Award 2026",
    "type": "Scholarship",
    "tags": {
      "state": "India",
      "gender": "All",
      "religion": "All",
      "class": [
        "Class 10",
        "Class 12",
        "UG",
        "PG"
      ]
    },
    "eligibility": "International students from India with international fee status, pursuing a full-time one-year postgraduate taught Master's programme in any discipline.",
    "scholarship_amount": "£12,500 tuition fee waiver for one year of study",
    "application_deadline": "01-Mar-2026",
    "apply_link": "https://www.gla.ac.uk/scholarships/indiaexcellenceaward/#eligiblecountries%2Fregions",
    "url": "https://www.buddy4study.com/scholarship/university-of-glasgow-india-excellence-award-2026"
  },
  {
    "scholarship_name": "Wells Mountain Foundation Scholarship 2026",
    "type": "Scholarship",
    "tags": {
      "state": "International",
      "gender": "All",
      "religion": "All",
      "class": [
        "Class 10",
        "Class 12",
        "UG",
        "PG"
      ]
    },
    "eligibility": "Applicants must be 35 years old or younger, have completed secondary education, be applying to a university or currently enrolled in classes for their first undergraduate degree, plan to live and work in their home country after graduation, have participated in volunteer service, and display the need for financial assistance.",
    "scholarship_amount": "Up to USD 3,000 per annum",
    "application_deadline": "01-Mar-2026",
    "apply_link": "https://www.buddy4study.com/scholarship/wells-mountain-foundation-scholarship-2026",
    "url": "https://www.buddy4study.com/scholarship/wells-mountain-foundation-scholarship-2026"
  },
  {
    "scholarship_name": "DAWN Rising Fellowships 2026",
    "type": "Scholarship",
    "tags": {
      "state": "International",
      "gender": "Female",
      "religion": "All",
      "class": [
        "UG",
        "PG"
      ]
    },
    "eligibility": "Women feminists under the age of 40 from the Global South.",
    "scholarship_amount": "USD 1,200 per month for 10 months",
    "application_deadline": "01-Mar-2026",
    "apply_link": "https://www.dawnfeminist.org/what-we-do/capacity-building/dawn-fellowship-for-young-women-feminists-from-the-global-south-2026",
    "url": "https://www.buddy4study.com/scholarship/dawn-rising-fellowships-2026"
  },
  {
    "scholarship_name": "ACU International Student Accommodation Scholarship",
    "type": "Scholarship",
    "tags": {
      "state": "All India",
      "gender": "All",
      "religion": "Minority",
      "class": [
        "Class 10",
        "Class 12",
        "UG",
        "PG",
        "PhD"
      ]
    },
    "eligibility": "International students are eligible for this scholarship.",
    "scholarship_amount": "Not specified",
    "application_deadline": "Not specified",
    "apply_link": "https://www.buddy4study.com/scholarship/acu-international-student-accommodation-scholarship#",
    "url": "https://www.buddy4study.com/scholarship/acu-international-student-accommodation-scholarship-2025"
  },
  {
    "scholarship_name": "Taiwan Visiting Program Fellowship 2026",
    "type": "Scholarship",
    "tags": {
      "state": "International",
      "gender": "All",
      "religion": "All",
      "class": [
        "PhD",
        "UG",
        "PG"
      ]
    },
    "eligibility": "Academics, postdoctoral researchers, and professionals working on Taiwan-related research fields are eligible for the fellowship.",
    "scholarship_amount": "Up to USD 30,000",
    "application_deadline": "01-Mar-2026",
    "apply_link": "https://aparc.fsi.stanford.edu/education/fellowship-and-training-opportunities/contemporary-taiwan-fellowships",
    "url": "https://www.buddy4study.com/scholarship/taiwan-visiting-program-fellowship-2026"
  },
  {
    "scholarship_name": "Stanford Next Asia Policy Visiting Fellowship 2026-2027",
    "type": "Scholarship",
    "tags": {
      "state": "United States",
      "gender": "All",
      "religion": "All",
      "class": [
        "Ph.D.",
        "Mid-career professionals"
      ]
    },
    "eligibility": "Applicants must be researchers or professionals from the Asia-Pacific region, hold a Ph.D. degree or demonstrate substantial professional achievement, have an ongoing affiliation with an external institution, and be proficient in English.",
    "scholarship_amount": "USD 30,000 supplementary stipend for one academic year",
    "application_deadline": "01-Mar-2026",
    "apply_link": "https://aparc.fsi.stanford.edu/education/fellowship-and-training-opportunities/stanford-next-asia-policy-lab-fellowships",
    "url": "https://www.buddy4study.com/scholarship/stanford-next-asia-policy-visiting-fellowship-2026"
  },
  {
    "scholarship_name": "President's PhD Scholarships, Imperial College London 2026-27",
    "type": "Scholarship",
    "tags": {
      "state": "United Kingdom",
      "gender": "All",
      "religion": "All",
      "class": [
        "Class 10",
        "Class 12",
        "UG",
        "PG",
        "PhD"
      ]
    },
    "eligibility": "Ph.D. applicants with a first-class or equivalent in an undergraduate or integrated Master’s degree, or a distinction in a standalone Master’s qualification.",
    "scholarship_amount": "Fully funded tuition with a stipend of GBP 26,500 per annum, a consumables fund of GBP 2,000 per annum, and other benefits.",
    "application_deadline": "02-Mar-2026",
    "apply_link": "https://www.imperial.ac.uk/study/fees-and-funding/postgraduate-doctoral/grants-scholarships/presidents-phd/#outcome",
    "url": "https://www.buddy4study.com/scholarship/presidents-phd-scholarships-imperial-college-london-2026"
  },
  {
    "scholarship_name": "Post-Matric Scholarship for ST, SC and MBC Students, Odisha 2025-26",
    "type": "Scholarship",
    "tags": {
      "state": "Odisha",
      "gender": "All",
      "religion": "Minority / SC/ST",
      "class": [
        "Class 10",
        "Class 12",
        "UG",
        "PG",
        "PhD"
      ]
    },
    "eligibility": "Applicant must be a domicile of Odisha, belong to a Scheduled Tribe (ST), Scheduled Caste (SC) or Minorities & Backward Classes (MBC), pursuing higher education in specified disciplines, and have an annual family income of not more than ₹2,50,000.",
    "scholarship_amount": "Financial assistance up to ₹5,50,000 per annum with an annual maintenance allowance of up to ₹13,500.",
    "application_deadline": "05-Mar-2026",
    "apply_link": "https://www.buddy4study.com/scholarship/postmatric-scholarship-for-st-sc-and-mbc-students-odisha-2025",
    "url": "https://www.buddy4study.com/scholarship/postmatric-scholarship-for-st-sc-and-mbc-students-odisha-2025"
  },
  {
    "scholarship_name": "Imperial College London Widening Participation Postgraduate Scholarship 2026-27",
    "type": "Scholarship",
    "tags": {
      "state": "United Kingdom",
      "gender": "All",
      "religion": "All",
      "class": [
        "Class 10",
        "Class 12",
        "UG",
        "PG",
        "PhD"
      ]
    },
    "eligibility": "International students pursuing a MRes program at Imperial College London are eligible.",
    "scholarship_amount": "£4,999 (one-time)",
    "application_deadline": "11-Mar-2026",
    "apply_link": "https://www.imperial.ac.uk/study/fees-and-funding/scholarships-search/widening-participation-postgraduate-scholarship-20262027.php",
    "url": "https://www.buddy4study.com/scholarship/imperial-college-london-widening-participation-postgraduate-scholarship-2026"
  },
  {
    "scholarship_name": "The British Academy International Fellowship 2026",
    "type": "Scholarship",
    "tags": {
      "state": "United Kingdom",
      "gender": "All",
      "religion": "All",
      "class": [
        "PhD",
        "UG",
        "PG"
      ]
    },
    "eligibility": "Applicants must hold a PhD from a non-UK university, have no more than five years of active full-time postdoctoral experience, be working outside the UK, not hold UK citizenship, be competent in oral and written English, and have a clearly defined and mutually-beneficial research proposal agreed with a UK host researcher.",
    "scholarship_amount": "Fellowship of up to £20,000, including full salary, research expenses of up to £12,000, and relocation costs of up to £8,000",
    "application_deadline": "11-Mar-2026",
    "apply_link": "https://www.thebritishacademy.ac.uk/funding/schemes/international-fellowships/",
    "url": "https://www.buddy4study.com/scholarship/the-british-academy-international-fellowship-2026"
  },
  {
    "scholarship_name": "University of Nottingham, UK International Undergraduate Excellence Scholarships 2026",
    "type": "Scholarship",
    "tags": {
      "state": "United Kingdom",
      "gender": "All",
      "religion": "All",
      "class": [
        "Class 10",
        "Class 12",
        "UG",
        "PG"
      ]
    },
    "eligibility": "International, self-funded, fee-payer students with AAA grades or international equivalent, holding an offer to begin a full-time undergraduate degree programme at the University of Nottingham, UK.",
    "scholarship_amount": "Up to GBP 2,000",
    "application_deadline": "11-Mar-2026",
    "apply_link": "https://www.buddy4study.com/scholarship/university-of-nottingham-uk-international-undergraduate-excellence-scholarships-2026",
    "url": "https://www.buddy4study.com/scholarship/university-of-nottingham-uk-international-undergraduate-excellence-scholarships-2026"
  },
  {
    "scholarship_name": "Tingshua University Amgen Scholars Program 2026",
    "type": "Scholarship",
    "tags": {
      "state": "China",
      "gender": "All",
      "religion": "All",
      "class": [
        "Class 10",
        "Class 12",
        "UG",
        "PG"
      ]
    },
    "eligibility": "Students enrolled in a Bachelor’s degree programme in Asian universities/colleges",
    "scholarship_amount": "CNY 10,000 (₹1,23,537 approx.) and other benefits",
    "application_deadline": "15-Mar-2026",
    "apply_link": "https://tsinghuaamgenscholars.com/2.html",
    "url": "https://www.buddy4study.com/scholarship/tingshua-university-amgen-scholars-program-2026"
  },
  {
    "scholarship_name": "Oskar Morgenstern Fellowship Program 2026",
    "type": "Scholarship",
    "tags": {
      "state": "United States",
      "gender": "All",
      "religion": "All",
      "class": [
        "Graduate",
        "PhD"
      ]
    },
    "eligibility": "Graduate students, scholars, and practitioners from any discipline with an interest in political economy and emerging technologies such as artificial intelligence.",
    "scholarship_amount": "$2,250 stipend and all required readings",
    "application_deadline": "15-Mar-2026",
    "apply_link": "https://www.mercatus.org/students/oskar-morgenstern-fellowship#2392643287-25203644",
    "url": "https://www.buddy4study.com/scholarship/oskar-morgenstern-fellowship-program-2026"
  },
  {
    "scholarship_name": "NGSF Internship Program 2025",
    "type": "Internship",
    "tags": {
      "state": "All India",
      "gender": "All",
      "religion": "All",
      "class": [
        "Class 10",
        "Class 12",
        "UG",
        "PG"
      ]
    },
    "eligibility": "Undergraduate/postgraduate students interested in life science-associated internships for a period of 2-3 months.",
    "scholarship_amount": "Up to ₹6,000 per month for on-site internships and ₹3,000 for remote internships.",
    "application_deadline": "15-Mar-2026",
    "apply_link": "https://www.buddy4study.com/scholarship/ngsf-internship-program-2025",
    "url": "https://www.buddy4study.com/scholarship/ngsf-internship-program-2025"
  },
  {
    "scholarship_name": "Frédéric Bastiat Fellowship 2026-27",
    "type": "Scholarship",
    "tags": {
      "state": "United States",
      "gender": "All",
      "religion": "All",
      "class": [
        "Master's",
        "Juris Doctor (JD)",
        "Doctoral (PhD)"
      ]
    },
    "eligibility": "Graduate students enrolled in master's, juris doctoral, or doctoral programs from any university, in any discipline, with an interest in public policy.",
    "scholarship_amount": "$5,000 for 1 year",
    "application_deadline": "15-Mar-2026",
    "apply_link": "https://www.mercatus.org/students/frederic-bastiat-fellowship#2392643287-447368638",
    "url": "https://www.buddy4study.com/scholarship/frederic-bastiat-fellowship-2026"
  },
  {
    "scholarship_name": "NIAS Fellowship 2026",
    "type": "Scholarship",
    "tags": {
      "state": "Netherlands",
      "gender": "All",
      "religion": "All",
      "class": [
        "UG",
        "PG",
        "PhD"
      ]
    },
    "eligibility": "International students with a PhD degree in humanities and social sciences, with at least three years of research experience.",
    "scholarship_amount": "Stipend, travel expenses, accommodation, NIAS Library, and facilities for the organisation of an Expert Workshop",
    "application_deadline": "16-Mar-2026",
    "apply_link": "https://nias.knaw.nl/fellowships/nias-individual-fellowship/",
    "url": "https://www.buddy4study.com/scholarship/nias-fellowship-2026"
  },
  {
    "scholarship_name": "Ashoka University Young India Fellowship 2026-27",
    "type": "Scholarship",
    "tags": {
      "state": "All India",
      "gender": "All",
      "religion": "All",
      "class": [
        "Class 10",
        "Class 12",
        "UG",
        "PG"
      ]
    },
    "eligibility": "Graduates and final-year undergraduate students holding a recognised undergraduate degree or equivalent in any discipline, or be a final-year undergraduate student who will complete their degree by summer 2026.",
    "scholarship_amount": "Partial or fully funded fellowship",
    "application_deadline": "23-Mar-2026",
    "apply_link": "https://apply.ashoka.edu.in/SocialLogin.aspx",
    "url": "https://www.buddy4study.com/scholarship/ashoka-university-young-india-fellowship-2026"
  },
  {
    "scholarship_name": "Ireland International Education Scholarship 2026-27",
    "type": "Scholarship",
    "tags": {
      "state": "International",
      "gender": "All",
      "religion": "All",
      "class": [
        "Master's",
        "Postgraduate Diploma",
        "PhD"
      ]
    },
    "eligibility": "Graduated students from non-EU/EEA countries with a conditional or final offer at the time of application.",
    "scholarship_amount": "Up to €10,000 (approximately ₹10,90,070)",
    "application_deadline": "12th Mar 2026",
    "apply_link": "https://webportalapp.com/sp/login/heagrantapplication_25",
    "url": "https://www.buddy4study.com/scholarship/ireland-international-education-scholarship-2026"
  },
  {
    "scholarship_name": "Classic IAS Academy Affordable Coaching Program 2024-25",
    "type": "Scholarship",
    "tags": {
      "state": "All India",
      "gender": "All",
      "religion": "All",
      "class": [
        "Class 10",
        "Class 12",
        "UG",
        "PG",
        "PhD"
      ]
    },
    "eligibility": "Students seeking to pursue an IAS coaching program",
    "scholarship_amount": "₹22,000 (66% waiver on the actual fee)",
    "application_deadline": "31-Mar-2026",
    "apply_link": "https://www.buddy4study.com/scholarship/classic-ias-academy-affordable-coaching-program-2024-25#apply",
    "url": "https://www.buddy4study.com/scholarship/classic-ias-academy-affordable-coaching-program-2024-25"
  },
  {
    "scholarship_name": "Post-Matric Scholarship for OBC Students, Delhi 2025-26",
    "type": "Scholarship",
    "tags": {
      "state": "Delhi",
      "gender": "All",
      "religion": "OBC",
      "class": [
        "Class 11",
        "Class 12",
        "UG",
        "PG"
      ]
    },
    "eligibility": "Indian citizen, domiciled in Delhi, OBC category, studying at post-matriculation/post-secondary level, annual parent(s)/guardian income not more than ₹1,00,000, and secured an attendance of at least 75% in the previous year.",
    "scholarship_amount": "Up to ₹750 per month with other benefits",
    "application_deadline": "31-May-2026",
    "apply_link": "http://www.edistrict.delhigovt.nic.in/",
    "url": "https://www.buddy4study.com/scholarship/postmatric-scholarship-for-obc-students-delhi-2025"
  },
  {
    "scholarship_name": "Vocational Training Fee Reimbursement for SC Students, Maharashtra 2025-26",
    "type": "Scholarship",
    "tags": {
      "state": "Maharashtra",
      "gender": "All",
      "religion": "SC",
      "class": [
        "Class 10",
        "Class 12",
        "UG",
        "PG",
        "PhD"
      ]
    },
    "eligibility": "SC category students of Maharashtra who have secured admission through the Centralised Admission Process (CAP) in government and private ITIs under the PPP scheme.",
    "scholarship_amount": "100% reimbursement of course fees",
    "application_deadline": "31-Mar-2026",
    "apply_link": "https://www.buddy4study.com/scholarship/vocational-training-fee-reimbursement-for-sc-students-maharashtra-2025",
    "url": "https://www.buddy4study.com/scholarship/vocational-training-fee-reimbursement-for-sc-students-maharashtra-2025"
  },
  {
    "scholarship_name": "Post-Matric Scholarship Scheme Government of India, Maharashtra 2025-26",
    "type": "Scholarship",
    "tags": {
      "state": "Maharashtra",
      "gender": "All",
      "religion": "ST",
      "class": [
        "Class 10",
        "UG",
        "PG",
        "PhD"
      ]
    },
    "eligibility": "Applicant must be a domicile of Maharashtra, belong to the Scheduled Tribe (ST) category, have passed Class 10, have an annual family income of not more than ₹2,50,000, and not have a gap of more than 2 years in their formal education.",
    "scholarship_amount": "Maintenance allowance and other grants, including ₹550 to ₹1,200 for Hostellers/Day Scholars, ₹240 for Reader Allowance, ₹160 for Escort Allowance, ₹160 for Special Pay, ₹240 for Mentally Retarded, Extra Coaching, ₹1,600 for Study Tours, ₹1,600 for Thesis Typing/Printing, and ₹1,200 for Book Grant.",
    "application_deadline": "31-Mar-2026",
    "apply_link": "https://mahadbt.maharashtra.gov.in/SchemeData/SchemeData?str=E9DDFA703C38E51A668ED132B54E2162E54C475F826D85C79DA948301E5F7772",
    "url": "https://www.buddy4study.com/scholarship/postmatric-scholarship-scheme-government-of-india-maharashtra-2025"
  },
  {
    "scholarship_name": "State Government Open Merit Scholarship, Maharashtra 2025-26",
    "type": "Scholarship",
    "tags": {
      "state": "Maharashtra",
      "gender": "All",
      "religion": "All",
      "class": [
        "Class 10",
        "Class 12",
        "UG",
        "PG"
      ]
    },
    "eligibility": "Class 12 passed students of Maharashtra with a minimum of 60% marks pursuing a graduation degree in Arts, Commerce, Science, or Law.",
    "scholarship_amount": "₹100 per month",
    "application_deadline": "31-Mar-2026",
    "apply_link": "https://mahadbt.maharashtra.gov.in/SchemeData/SchemeData?str=E9DDFA703C38E51AED33CA69606C0CC2EF25388FB8EC7046E5E9B1E993657CEB",
    "url": "https://www.buddy4study.com/scholarship/state-government-open-merit-scholarship-maharashtra-2025"
  },
  {
    "scholarship_name": "Tuition Fee and Examination Fee for Tribal Students (Freeship), Maharashtra 2025-26",
    "type": "Scholarship",
    "tags": {
      "state": "Maharashtra",
      "gender": "All",
      "religion": "ST",
      "class": [
        "Class 10",
        "Class 12",
        "UG",
        "PG"
      ]
    },
    "eligibility": "Applicants must be a domicile of Maharashtra, belong to the Scheduled Tribe (ST) category, be studying at the post-matric level at a recognised institution, and have an annual family income of no more than ₹2,50,000.",
    "scholarship_amount": "Reimbursement for tuition and exam fees according to the approved fee structure of the respective college or institution.",
    "application_deadline": "31-Mar-2026",
    "apply_link": "https://mahadbt.maharashtra.gov.in/SchemeData/SchemeData?str=E9DDFA703C38E51AE7C10C1B9446574716EB93196C4CB29808753F77C61BEF29",
    "url": "https://www.buddy4study.com/scholarship/tuition-fee-and-examination-fee-for-tribal-students-freeship-maharashtra-2025"
  },
  {
    "scholarship_name": "Scholarship to Meritorious Students Possessing Mathematics/Physics, Maharashtra 2025-26",
    "type": "Scholarship",
    "tags": {
      "state": "Maharashtra",
      "gender": "All",
      "religion": "All",
      "class": [
        "Class 10",
        "Class 12",
        "UG",
        "PG"
      ]
    },
    "eligibility": "Indian national, domicile of Maharashtra, secured at least 60% marks in Science stream of Class 12, pursuing graduation degree in Science with Mathematics and Physics as main subjects",
    "scholarship_amount": "₹100 per month",
    "application_deadline": "31-Mar-2026",
    "apply_link": "https://mahadbt.maharashtra.gov.in/SchemeData/SchemeData?str=E9DDFA703C38E51AE50D4D8851DF49C43E0ED43F316413C64DC359D08045E4DB",
    "url": "https://www.buddy4study.com/scholarship/scholarship-to-meritorious-students-possessing-mathematics-physics-maharashtra-2025"
  },
  {
    "scholarship_name": "Government Vidyaniketan Scholarship, Maharashtra 2025-26",
    "type": "Scholarship",
    "tags": {
      "state": "Maharashtra",
      "gender": "All",
      "religion": "All",
      "class": [
        "Class 10",
        "UG",
        "PG"
      ]
    },
    "eligibility": "Class 10 passed students from Government Vidhyaniketan who are Indian nationals and domicile of Maharashtra with 60% marks in Class 10 board exams.",
    "scholarship_amount": "₹100 per month",
    "application_deadline": "31-Mar-2026",
    "apply_link": "https://mahadbt.maharashtra.gov.in/SchemeData/SchemeData?str=E9DDFA703C38E51A63C8EB5C6B8591A03ACAAA73B08A2E9A0140E826A54AE104",
    "url": "https://www.buddy4study.com/scholarship/government-vidyaniketan-scholarship-maharashtra-2025"
  },
  {
    "scholarship_name": "State Government Daxshina Adhichatra Scholarship, Maharashtra 2025-26",
    "type": "Scholarship",
    "tags": {
      "state": "Maharashtra",
      "gender": "All",
      "religion": "All",
      "class": [
        "UG",
        "PG"
      ]
    },
    "eligibility": "Students pursuing postgraduate courses in designated institutions, domicile of Maharashtra, graduate from government institutes and colleges/non-agricultural university of Maharashtra.",
    "scholarship_amount": "₹250 per month",
    "application_deadline": "31-Mar-2026",
    "apply_link": "https://www.buddy4study.com/scholarship/state-government-daxshina-adhichatra-scholarship-maharashtra-2025-26",
    "url": "https://www.buddy4study.com/scholarship/state-government-daxshina-adhichatra-scholarship-maharashtra-2025-26"
  },
  {
    "scholarship_name": "Government Research Adhichatra, Maharashtra 2025-26",
    "type": "Scholarship",
    "tags": {
      "state": "Maharashtra",
      "gender": "All",
      "religion": "All",
      "class": [
        "UG",
        "PG",
        "PhD"
      ]
    },
    "eligibility": "Indian citizen, domiciled in Maharashtra, postgraduate degree holder with 60% marks, currently enrolled in a Maharashtra institution",
    "scholarship_amount": "₹750 monthly scholarship and ₹1,000 annual stipend for additional expenses",
    "application_deadline": "31-Mar-2026",
    "apply_link": "https://mahadbt.maharashtra.gov.in/SchemeData/SchemeData?str=E9DDFA703C38E51AF8D6D26D8FA7FEBA8680F51C3601BE8CE372C",
    "url": "https://www.buddy4study.com/scholarship/government-research-adhichatra-maharashtra-2025"
  },
  {
    "scholarship_name": "Rajarshi Chhatrapati Shahu Maharaj Merit Scholarship for VJNT and SBC Category",
    "type": "Scholarship",
    "tags": {
      "state": "Maharashtra",
      "gender": "All",
      "religion": "Minority (VJNT and SBC category)",
      "class": [
        "Class 11",
        "Class 12",
        "UG",
        "PG"
      ]
    },
    "eligibility": "Indian citizen, domicile of Maharashtra, belonging to VJNT or SBC category, studying in Class 11 and 12, secured 75% and above marks in Class 10 examination",
    "scholarship_amount": "₹300 per month for 10 months",
    "application_deadline": "31-Mar-2026",
    "apply_link": "https://mahadbt.maharashtra.gov.in/SchemeData/SchemeData?str=E9DDFA703C38E51A91E82A5FCFBAAB0483A",
    "url": "https://www.buddy4study.com/scholarship/rajarshi-chhatrapati-shahu-maharaj-merit-scholarship-for-vjnt-and-sbc-category-maharashtra-2025"
  },
  {
    "scholarship_name": "Post-Matric Scholarship to SBC Students, Maharashtra 2025-26",
    "type": "Scholarship",
    "tags": {
      "state": "Maharashtra",
      "gender": "All",
      "religion": "All",
      "class": [
        "Class 11",
        "Class 12",
        "UG",
        "PG",
        "PhD"
      ]
    },
    "eligibility": "Indian citizen, domicile of Maharashtra, Special Backward Classes (SBC) category, pursuing post-matric studies with 75% attendance and annual family income less than or equal to ₹1,50,000",
    "scholarship_amount": "Monthly maintenance allowance up to ₹425 and other benefits",
    "application_deadline": "31-Mar-2026",
    "apply_link": "https://www.buddy4study.com/scholarship/postmatric-scholarship-to-sbc-students-maharashtra-2025",
    "url": "https://www.buddy4study.com/scholarship/postmatric-scholarship-to-sbc-students-maharashtra-2025"
  },
  {
    "scholarship_name": "Tuition Fees and Examination Fees to OBC Students, Maharashtra 2025-26",
    "type": "Scholarship",
    "tags": {
      "state": "Maharashtra",
      "gender": "All",
      "religion": "All",
      "class": [
        "Class 11",
        "Class 12",
        "UG",
        "PG",
        "PhD"
      ]
    },
    "eligibility": "Indian citizen, domicile of Maharashtra, OBC category, pursuing post-matric studies in government/government-aided/private institution, annual family income less than or equal to ₹8,00,000",
    "scholarship_amount": "Up to 100% reimbursement in tuition, exams, and other admissible fees",
    "application_deadline": "31-Mar-2026",
    "apply_link": "https://www.buddy4study.com/scholarship/tuition-fees-and-examination-fees-to-obc-students-maharashtra-2025-26",
    "url": "https://www.buddy4study.com/scholarship/tuition-fees-and-examination-fees-to-obc-students-maharashtra-2025-26"
  },
  {
    "scholarship_name": "Vocational Training Fee Reimbursement for OBC, SEBC, VJNT & SBC Students, Maharashtra 2025-26",
    "type": "Scholarship",
    "tags": {
      "state": "Maharashtra",
      "gender": "All",
      "religion": "Minority",
      "class": [
        "Class 10",
        "Class 12",
        "UG",
        "PG",
        "PhD"
      ]
    },
    "eligibility": "Students belonging to OBC, SEBC, VJNT, and SBC categories who are pursuing vocational training courses and are domicile of Maharashtra.",
    "scholarship_amount": "80% course fees",
    "application_deadline": "31-Mar-2026",
    "apply_link": "https://www.buddy4study.com/scholarship/vocational-training-fee-reimbursement-for-obc-sebc-vjnt-sbc-students-maharashtra-2025#apply",
    "url": "https://www.buddy4study.com/scholarship/vocational-training-fee-reimbursement-for-obc-sebc-vjnt-sbc-students-maharashtra-2025"
  },
  {
    "scholarship_name": "Rajarshri Chhatrapati Shahu Maharaj Fee Reimbursement Scholarship Scheme",
    "type": "Scholarship",
    "tags": {
      "state": "Maharashtra",
      "gender": "All",
      "religion": "All",
      "class": [
        "Class 10",
        "Class 12",
        "UG",
        "PG",
        "PhD"
      ]
    },
    "eligibility": "EBC category students applying for specified UG medical degree courses in Maharashtra",
    "scholarship_amount": "50% reimbursement of tuition and development fees",
    "application_deadline": "31-Mar-2026",
    "apply_link": "https://www.buddy4study.com/scholarship/rajarshri-chhatrapati-shahu-maharaj-fee-reimbursement-scholarship-scheme-maharashtra-2025",
    "url": "https://www.buddy4study.com/scholarship/rajarshri-chhatrapati-shahu-maharaj-fee-reimbursement-scholarship-scheme-maharashtra-2025"
  },
  {
    "scholarship_name": "Dr. Panjabrao Deshmukh Hostel Maintenance Allowance Scheme, Maharashtra",
    "type": "Scholarship",
    "tags": {
      "state": "Maharashtra",
      "gender": "All",
      "religion": "All",
      "class": [
        "Class 10",
        "Class 12",
        "UG",
        "PG",
        "PhD"
      ]
    },
    "eligibility": "Applicants must be permanent residents of Maharashtra, children of registered labourers and/or Alpabhudharak shetkari, and pursuing specified medical courses in government-aided, corporation, or private unaided colleges.",
    "scholarship_amount": "Hostel maintenance allowance up to ₹30,000 per annum",
    "application_deadline": "31-Mar-2026",
    "apply_link": "https://www.buddy4study.com/scholarship/dr-panjabrao-deshmukh-hostel-maintenance-allowance-scheme-maharashtra-2025",
    "url": "https://www.buddy4study.com/scholarship/dr-panjabrao-deshmukh-hostel-maintenance-allowance-scheme-maharashtra-2025"
  },
  {
    "scholarship_name": "MAFSU Rajarshi Chhatrapati Shahu Maharaj Shikshan Shulkh Shishyavrutti Yojna (EBC) Students, Maharashtra 2025-26",
    "type": "Scholarship",
    "tags": {
      "state": "Maharashtra",
      "gender": "All",
      "religion": "All",
      "class": [
        "Class 10",
        "Class 12",
        "UG",
        "PG",
        "PhD"
      ]
    },
    "eligibility": "Applicants must be a domicile of Maharashtra, a 'Bonafide Student of the Institute', enrolled in a professional and technical course (UG/PG degree) in a recognised educational institution, with an annual family income of not more than ₹8,00,000.",
    "scholarship_amount": "Reimbursement of up to 100% tuition and exam fees",
    "application_deadline": "31-Mar-2026",
    "apply_link": "https://www.buddy4study.com/scholarship/mafsu-rajarshi-chhatrapati-shahu-maharaj-shikshan-shulkh-shishyavrutti-yojna-ebc-students-maharashtra-2025-26",
    "url": "https://www.buddy4study.com/scholarship/mafsu-rajarshi-chhatrapati-shahu-maharaj-shikshan-shulkh-shishyavrutti-yojna-ebc-students-maharashtra-2025-26"
  },
  {
    "scholarship_name": "Mahindra Saarthi Abhiyaan 2025-26",
    "type": "Scholarship",
    "tags": {
      "state": "All India",
      "gender": "All",
      "religion": "All",
      "class": [
        "Class 10",
        "Class 12",
        "UG",
        "PG",
        "PhD"
      ]
    },
    "eligibility": "Eligibility criteria not explicitly mentioned",
    "scholarship_amount": "Not explicitly mentioned",
    "application_deadline": "Always Open",
    "apply_link": "https://www.buddy4study.com/scholarship/mahindra-saarthi-abhiyaan-2025-26#apply",
    "url": "https://www.buddy4study.com/scholarship/mahindra-saarthi-abhiyaan-2025-26"
  },
  {
    "scholarship_name": "Mahindra Saarthi Abhiyaan 2025-26",
    "type": "Scholarship",
    "tags": {
      "state": "All India",
      "gender": "All",
      "religion": "All",
      "class": [
        "Class 10",
        "Class 12",
        "UG",
        "PG",
        "PhD"
      ]
    },
    "eligibility": "Eligibility not explicitly mentioned",
    "scholarship_amount": "Not explicitly mentioned",
    "application_deadline": "Always Open",
    "apply_link": "https://www.buddy4study.com/scholarship/mahindra-saarthi-abhiyaan-2025-26#apply",
    "url": "https://www.buddy4study.com/scholarship/mahindra-saarthi-abhiyaan-2025-26"
  },
  {
    "scholarship_name": "BGM Pashu Seva Scholarship Program",
    "type": "Scholarship",
    "tags": {
      "state": "All India",
      "gender": "All",
      "religion": "All",
      "class": [
        "Class 10",
        "Class 12",
        "UG",
        "PG",
        "PhD"
      ]
    },
    "eligibility": "Eligibility criteria not explicitly mentioned",
    "scholarship_amount": "Not explicitly mentioned",
    "application_deadline": "Always Open",
    "apply_link": "https://www.buddy4study.com/scholarship/bgm-pashu-seva-scholarship-program-1#apply",
    "url": "https://www.buddy4study.com/scholarship/bgm-pashu-seva-scholarship-program-1"
  },
  {
    "scholarship_name": "BGM Pashu Seva Scholarship Program",
    "type": "Scholarship",
    "tags": {
      "state": "All India",
      "gender": "All",
      "religion": "All",
      "class": [
        "Class 10",
        "Class 12",
        "UG",
        "PG",
        "PhD"
      ]
    },
    "eligibility": "Eligibility criteria not explicitly mentioned",
    "scholarship_amount": "Not explicitly mentioned",
    "application_deadline": "Always Open",
    "apply_link": "https://www.buddy4study.com/scholarship/bgm-pashu-seva-scholarship-program-1#apply",
    "url": "https://www.buddy4study.com/scholarship/bgm-pashu-seva-scholarship-program-1"
  },
  {
    "scholarship_name": "Kind Circle Scholarship for Meritorious Students 2025-26",
    "type": "Scholarship",
    "tags": {
      "state": "All India",
      "gender": "All",
      "religion": "All",
      "class": [
        "Class 10",
        "Class 12",
        "UG",
        "PG",
        "PhD"
      ]
    },
    "eligibility": "Eligibility criteria not explicitly mentioned",
    "scholarship_amount": "Not explicitly mentioned",
    "application_deadline": "Always Open",
    "apply_link": "https://www.buddy4study.com/scholarship/kind-circle-scholarship-for-meritorious-students-2025-26#apply",
    "url": "https://www.buddy4study.com/scholarship/kind-circle-scholarship-for-meritorious-students-2025-26"
  },
  {
    "scholarship_name": "Kind Circle Scholarship for Meritorious Students 2025-26",
    "type": "Scholarship",
    "tags": {
      "state": "All India",
      "gender": "All",
      "religion": "All",
      "class": [
        "Class 10",
        "Class 12",
        "UG",
        "PG"
      ]
    },
    "eligibility": "Eligibility criteria not explicitly mentioned",
    "scholarship_amount": "Not explicitly mentioned",
    "application_deadline": "Always Open",
    "apply_link": "https://www.buddy4study.com/scholarship/kind-circle-scholarship-for-meritorious-students-2025-26#apply",
    "url": "https://www.buddy4study.com/scholarship/kind-circle-scholarship-for-meritorious-students-2025-26"
  }
]